{
  "participants": [
    {
      "name": "Хозе-Рауль Капабланка",
      "title": "Чемпион мира по шахматам",
      "img": "src/assets/images/statics/Group 16.png"
    },
    {
      "name": "Эммануил Ласкер",
      "title": "Чемпион мира по шахматам",
      "img": "src/assets/images/statics/Group 16.png"
    },
    {
      "name": "Александр Алехин",
      "title": "Чемпион мира по шахматам",
      "img": "src/assets/images/statics/Group 16.png"
    }
  ],
  "events": [
    {
      "date": "22 июня 1927 г. в 18:00",
      "location": "Клуб «Картонжник»",
      "ticketPrice": "20 коп.",
      "gameFee": "50",
      "orgPrice": "100",
      "telegramFee": "21 руб. 16 коп.",
      "adminContact": "К. Михельсону"
    }
  ],
  "promo": {
    "heading": "Чтобы поддержать международный Васюкинский турнир посетите лекцию на тему:",
    "subHeading": "«Плодотворная дебютная идея»"
  },
  "steps": [
    { "number": 1, "text": "Строительство железнодорожной магистрали Москва-Васюки" },
    { "number": 2, "text": "Открытие фешенебельной гостиницы «Проходная пешка» и других небоскребов" },
    { "number": 3, "text": "Поднятие сельского хозяйства в радиусе на тысячу километров: производство овощей, фруктов, икры, шоколадных конфет" },
    { "number": 4, "text": "Строительство дворца для турнира" },
    { "number": 5, "text": "Размещение гаражей для гостевого автотранспорта" },
    { "number": 6, "text": "Постройка сверхмощной радиостанции для передачи всему миру сенсационных результатов" },
    { "number": 7, "text": "Создание аэропорта «Большие Васюки» с регулярным отправлением почтовых самолетов и дирижаблей во все концы света, включая Лос-Анджелес и Мельбурн" }
  ]
}
